DataSort/DS.py
DataSort/__init__.py
DataSort-0.0.1.dist-info/LICENSE
DataSort-0.0.1.dist-info/METADATA
DataSort-0.0.1.dist-info/WHEEL
DataSort-0.0.1.dist-info/top_level.txt
DataSort-0.0.1.dist-info/RECORD
